{
    "DbMetaData": [
        {
            "DbName": "metadata",
            "DbPath": "Assets/StreamingAssets",
            "TableNames": [
                "Metadata"
            ],
            "DbHandlerGOName": "",
            "DbContextName": "",
            "CreatedAt": ""
        },
        {
            "DbName": "sites",
            "DbPath": "Assets/StreamingAssets",
            "TableNames": [
                "SiteScene",
                "Site"
            ],
            "DbHandlerGOName": "",
            "DbContextName": "",
            "CreatedAt": ""
        }
    ]
}